mailadm/__init__.py
mailadm/app.py
mailadm/cmdline.py
mailadm/conn.py
mailadm/db.py
mailadm/gen_qr.py
mailadm/mailcow.py
mailadm/util.py
mailadm/web.py
mailadm/data/delta-chat-bw.png
mailadm/data/delta-chat-red.png
mailadm/data/opensans-regular.ttf
mailadm-0.11.0.dist-info/LICENSE
mailadm-0.11.0.dist-info/METADATA
mailadm-0.11.0.dist-info/WHEEL
mailadm-0.11.0.dist-info/entry_points.txt
mailadm-0.11.0.dist-info/top_level.txt
mailadm-0.11.0.dist-info/RECORD
