Metadata-Version: 2.1
Name: mailadm
Version: 0.11.0
Summary: web API and CLI tool for automatic e-mail user creation/deletion
Home-page: https://github.com/deltachat/mailadm
Author: holger, missytake
Author-email: holger@merlinux.eu, missytake@systemli.org
License-File: LICENSE
Requires-Dist: deltachat
Requires-Dist: click (>=6.0)
Requires-Dist: flask
Requires-Dist: pillow
Requires-Dist: qrcode
Requires-Dist: gunicorn
Requires-Dist: requests
Requires-Dist: imapclient
